alxhttp/__init__.py
alxhttp/__init__.pyi
alxhttp/cookies.py
alxhttp/cookies.pyi
alxhttp/errors.py
alxhttp/errors.pyi
alxhttp/file.py
alxhttp/file.pyi
alxhttp/file_watcher.py
alxhttp/file_watcher.pyi
alxhttp/headers.py
alxhttp/headers.pyi
alxhttp/json.py
alxhttp/json.pyi
alxhttp/logging.py
alxhttp/logging.pyi
alxhttp/py.typed
alxhttp/req_id.py
alxhttp/req_id.pyi
alxhttp/schemas.py
alxhttp/schemas.pyi
alxhttp/server.py
alxhttp/server.pyi
alxhttp/sql.py
alxhttp/sql.pyi
alxhttp/xray.py
alxhttp/xray.pyi
alxhttp/middleware/__init__.py
alxhttp/middleware/__init__.pyi
alxhttp/middleware/assign_req_id.py
alxhttp/middleware/assign_req_id.pyi
alxhttp/middleware/defaults.py
alxhttp/middleware/defaults.pyi
alxhttp/middleware/ensure_json_errors.py
alxhttp/middleware/ensure_json_errors.pyi
alxhttp/middleware/g_state.py
alxhttp/middleware/gzip_compression.py
alxhttp/middleware/pydantic_validation.py
alxhttp/middleware/pydantic_validation.pyi
alxhttp/middleware/req_res_logger.py
alxhttp/middleware/save_json.py
alxhttp/middleware/security_headers.py
alxhttp/middleware/security_headers.pyi
alxhttp/middleware/unhandled_errors.py
alxhttp/middleware/unhandled_errors.pyi
alxhttp/pydantic/__init__.py
alxhttp/pydantic/__init__.pyi
alxhttp/pydantic/basemodel.py
alxhttp/pydantic/basemodel.pyi
alxhttp/pydantic/request.py
alxhttp/pydantic/response.py
alxhttp/pydantic/route.py
alxhttp/pydantic/ws_request.py
alxhttp/pydantic/ws_route.py
alxhttp/tests/__init__.py
alxhttp/tests/__init__.pyi
alxhttp/tests/multipart_bytes_writer.py
alxhttp/tests/stream_reader.py
alxhttp/typescript/__init__.py
alxhttp/typescript/__init__.pyi
alxhttp/typescript/basic_syntax.py
alxhttp/typescript/syntax_tree.py
alxhttp/typescript/type_checks.py
alxhttp/typescript/type_checks.pyi
alxhttp/typescript/type_conversion.py
alxhttp/typescript/type_index.py
alxhttp/typescript/types.py
alxhttp/typescript/types.pyi
alxhttp/typescript/writer.py
alxhttp/typescript/wrappers/__init__.py
alxhttp-0.9.95.dist-info/licenses/LICENSE
alxhttp-0.9.95.dist-info/METADATA
alxhttp-0.9.95.dist-info/WHEEL
alxhttp-0.9.95.dist-info/top_level.txt
alxhttp-0.9.95.dist-info/RECORD
