Metadata-Version: 2.4
Name: alxhttp
Version: 0.9.95
Summary: A better base server for AioHTTP
Author-email: Alexander Macdonald <alex@alexmac.cc>
License-Expression: MIT
Project-URL: Homepage, https://github.com/alexmac/alxhttp
Classifier: Programming Language :: Python :: 3
Classifier: Operating System :: OS Independent
Requires-Python: >=3.13
License-File: LICENSE
Requires-Dist: asyncpg-stubs>=0.30.2
Requires-Dist: basedpyright>=1.31.4
Requires-Dist: pip>=25.0.1
Requires-Dist: pytest-cov>=6.0.0
Requires-Dist: pytest-mock>=3.14.0
Requires-Dist: pytest>=8.3.4
Requires-Dist: aiohttp~=3.9
Requires-Dist: asyncpg~=0.29
Requires-Dist: pglast~=7.7
Requires-Dist: pydantic~=2.7
Requires-Dist: pyhumps~=3.8
Requires-Dist: redis~=6.4
Requires-Dist: watchdog~=6.0
Requires-Dist: twine>=6.2.0
Requires-Dist: ty>=0.0.2
Provides-Extra: xray
Requires-Dist: aws-xray-sdk>=2.13; extra == "xray"
Dynamic: license-file
